{"com\\stackmc\\subserver\\instance\\InstanceType$InstanciableWorld.class":1741947810974,"com\\stackmc\\subserver\\instance\\EventDispatcher$Dispatchable.class":1741947810976,"com\\stackmc\\subserver\\commands\\subs\\LoadSubCommand.class":1741947810974,"com\\stackmc\\subserver\\instance\\Instance$InstanciableWorld.class":1741947810967,"com\\stackmc\\subserver\\listeners\\InstanceListener.class":1741947810967,"com\\stackmc\\subserver\\commands\\subs\\CloseSubCommand.class":1741947810961,"com\\stackmc\\subserver\\commands\\subs\\TpSubCommand.class":1741947810970,"com\\stackmc\\subserver\\instance\\InstanceState.class":1741947810974,"com\\stackmc\\subserver\\commands\\AbstractCommand.class":1741947810964,"com\\stackmc\\subserver\\worldgen\\SWMUtils.class":1741947810971,"com\\stackmc\\subserver\\instance\\InstanceFactory.class":1741947810974,"com\\stackmc\\subserver\\instance\\InstanceType.class":1741947810968,"com\\stackmc\\subserver\\listeners\\EventListener.class":1741947810976,"com\\stackmc\\subserver\\instance\\Instance.class":1741947810975,"com\\stackmc\\subserver\\commands\\subs\\ListSubCommand.class":1741947810962,"com\\stackmc\\subserver\\SubServer.class":1741947810964,"com\\stackmc\\subserver\\instance\\EventDispatcher.class":1741947810965,"com\\stackmc\\subserver\\commands\\SubServerCommand.class":1741947810956}